{
  "app_name": "facebook",
  "facebook_marketplace": {
    "contacted_items": [
      {
        "item_title": "PC",
        "last_inbound_message": null,
        "last_outbound_message": "Hi, is this available?",
        "last_updated": "2026-03-26T01:10:55-07:00",
        "location_hint": null,
        "message_status": "message_sent",
        "seen_status": null,
        "seller_name": "Joshua",
        "seller_rating": null,
        "thread_key": "joshua-pc"
      },
      {
        "image_label": "Product Image,1 of 7",
        "item_title": "HP Omen Max 16 - 5080, i7 255hx, 32gb ram, 512 gb + 2tb ssds, 240hz 2560x1600p OLED screen, wifi 7",
        "last_inbound_message": null,
        "last_outbound_message": "i7 255hx, 32gb ram, 512 gb + 2tb ssds, 240hz 2560x1600p OLED screen, wifi 7",
        "last_updated": "2026-03-26T00:49:13-07:00",
        "location_hint": null,
        "message_status": "sent",
        "price": "$1,900",
        "seller_name": null,
        "seller_rating": null,
        "thread_key": "hp-omen-max-16-5080-i7-255hx-32gb-ram-512-gb-2tb-ssds-240hz-2560x1600p-oled-screen-wifi-7"
      },
      {
        "image_label": "Product Image,1 of 7",
        "item_title": "2021 MacBook Pro M1 Pro chip",
        "last_inbound_message": null,
        "last_outbound_message": null,
        "last_updated": "2026-03-26T00:47:08-07:00",
        "location_hint": null,
        "message_status": "sent",
        "price": "$800",
        "seller_name": null,
        "seller_rating": null,
        "thread_key": "2021-macbook-pro-m1-pro-chip"
      },
      {
        "image_label": "Product Image,1 of 1",
        "item_title": "motherboard with cpu and ram",
        "last_inbound_message": null,
        "last_outbound_message": null,
        "last_updated": "2026-03-26T00:43:16-07:00",
        "location_hint": null,
        "message_status": "sent",
        "price": "$300",
        "seller_name": null,
        "seller_rating": null,
        "thread_key": "motherboard-with-cpu-and-ram"
      },
      {
        "image_label": "Product Image,1 of 9",
        "item_title": "Apple MacBook Pro 16\" A2141 2019 \u2013 i9 2.30GHz \u2013 32GB RAM \u2013 1TB SSD \u2013 Retina EUC",
        "last_inbound_message": null,
        "last_outbound_message": null,
        "last_updated": "2026-03-26T00:40:17-07:00",
        "location_hint": null,
        "message_status": "sent",
        "price": "$429",
        "seller_name": "Just listed",
        "seller_rating": null,
        "thread_key": "apple-macbook-pro-16-a2141-2019-i9-2-30ghz-32gb-ram-1tb-ssd-retina-euc"
      },
      {
        "image_label": null,
        "item_title": "Alienware m16 R2 Gaming Laptop | Ultra 9 | RTX 4070 | 32GB RAM | 1TB SSD | 240Hz QHD | 2025",
        "last_inbound_message": null,
        "last_outbound_message": null,
        "last_updated": "2026-03-26T00:39:04-07:00",
        "location_hint": null,
        "message_status": "sent",
        "price": "$1,150",
        "seller_name": null,
        "seller_rating": null,
        "thread_key": "alienware-m16-r2-gaming-laptop-ultra-9-rtx-4070-32gb-ram-1tb-ssd-240hz-qhd-2025"
      },
      {
        "image_label": "Product Image,1 of 3",
        "item_title": "MacBook Pro 15\" 2017 (A1707) \u2013 i7, 16GB RAM, 500GB SSD",
        "last_inbound_message": null,
        "last_outbound_message": "16GB RAM, 500GB SSD",
        "last_updated": "2026-03-26T00:31:44-07:00",
        "location_hint": null,
        "message_status": "sent",
        "price": "$230",
        "seller_name": "Just listed",
        "seller_rating": null,
        "thread_key": "macbook-pro-15-2017-a1707-i7-16gb-ram-500gb-ssd"
      },
      {
        "image_label": "Product Image,1 of 3",
        "item_title": "[Full PC] 32GB DDR5 RAM / Ryzen 5 7600 / RX 6700 XT /",
        "last_inbound_message": null,
        "last_outbound_message": null,
        "last_updated": "2026-03-26T00:28:39-07:00",
        "location_hint": null,
        "message_status": "sent",
        "price": "$1,100",
        "seller_name": null,
        "seller_rating": null,
        "thread_key": "full-pc-32gb-ddr5-ram-ryzen-5-7600-rx-6700-xt"
      },
      {
        "image_label": "Product Image,1 of 2",
        "item_title": "2023 MacBook pro",
        "last_inbound_message": null,
        "last_outbound_message": null,
        "last_updated": "2026-03-26T00:21:19-07:00",
        "location_hint": null,
        "message_status": "sent",
        "price": "$1,200",
        "seller_name": null,
        "seller_rating": null,
        "thread_key": "2023-macbook-pro"
      },
      {
        "image_label": "Product Image,1 of 1",
        "item_title": "Sony lens",
        "last_inbound_message": null,
        "last_outbound_message": null,
        "last_updated": "2026-03-26T00:19:26-07:00",
        "location_hint": null,
        "message_status": "sent",
        "price": "$1,700",
        "seller_name": "Just listed",
        "seller_rating": null,
        "thread_key": "sony-lens"
      },
      {
        "image_label": "Product Image,1 of 6",
        "item_title": "iPhone 13 Pro Max",
        "last_inbound_message": null,
        "last_outbound_message": null,
        "last_updated": "2026-03-26T00:18:09-07:00",
        "location_hint": null,
        "message_status": "sent",
        "price": "$350",
        "seller_name": "Just listed",
        "seller_rating": null,
        "thread_key": "iphone-13-pro-max"
      },
      {
        "image_label": "Product Image,1 of 4",
        "item_title": "Apple iPhone 14 Pro 5G Unlocked",
        "last_inbound_message": null,
        "last_outbound_message": null,
        "last_updated": "2026-03-26T00:17:28-07:00",
        "location_hint": null,
        "message_status": "sent",
        "price": "$420",
        "seller_name": null,
        "seller_rating": null,
        "thread_key": "apple-iphone-14-pro-5g-unlocked"
      },
      {
        "image_label": "Product Image,1 of 3",
        "item_title": "Monitor 32\" 4K UHD 3840x2160",
        "last_inbound_message": null,
        "last_outbound_message": null,
        "last_updated": "2026-03-26T00:14:52-07:00",
        "location_hint": null,
        "message_status": "sent",
        "price": "$200",
        "seller_name": "Just listed",
        "seller_rating": null,
        "thread_key": "monitor-32-4k-uhd-3840x2160"
      },
      {
        "image_label": "Product Image,1 of 2",
        "item_title": "RTX 3060 Gaming PC",
        "last_inbound_message": null,
        "last_outbound_message": null,
        "last_updated": "2026-03-26T00:13:03-07:00",
        "location_hint": null,
        "message_status": "sent",
        "price": "$650",
        "seller_name": "Just listed",
        "seller_rating": null,
        "thread_key": "rtx-3060-gaming-pc"
      },
      {
        "item_title": "Gaming PC",
        "last_inbound_message": "No",
        "last_outbound_message": "350?",
        "last_updated": "2026-03-25T23:01:51-07:00",
        "location_hint": null,
        "message_status": "seller_replied",
        "seen_status": "Seen by Brandon Pellham",
        "seller_name": "Brandon",
        "seller_rating": "4.2 (5 reviews of Brandon)",
        "thread_key": "brandon-gaming-pc"
      },
      {
        "image_label": "Product Image,1 of 7",
        "item_title": "Dell 27 Inch USB-C Hub Computer Monitor - P2723DE",
        "last_inbound_message": null,
        "last_outbound_message": null,
        "last_updated": "2026-03-25T14:56:09-07:00",
        "location_hint": null,
        "message_status": "sent",
        "price": "$100",
        "seller_name": "Just listed",
        "seller_rating": null,
        "thread_key": "dell-27-inch-usb-c-hub-computer-monitor-p2723de"
      },
      {
        "image_label": "Product Image,1 of 2",
        "item_title": "Apple iPhone 16 Pro Max \u2013 256GB \u2013 White \u2013 Excellent Condition",
        "last_inbound_message": null,
        "last_outbound_message": null,
        "last_updated": "2026-03-25T14:55:29-07:00",
        "location_hint": null,
        "message_status": "sent",
        "price": "$700",
        "seller_name": "Just listed",
        "seller_rating": null,
        "thread_key": "apple-iphone-16-pro-max-256gb-white-excellent-condition"
      },
      {
        "image_label": "Product Image,1 of 5",
        "item_title": "Microsoft Surface Laptop 4 32GB 1TB SSD",
        "last_inbound_message": null,
        "last_outbound_message": null,
        "last_updated": "2026-03-25T14:54:48-07:00",
        "location_hint": null,
        "message_status": "sent",
        "price": "$350",
        "seller_name": "Just listed",
        "seller_rating": null,
        "thread_key": "microsoft-surface-laptop-4-32gb-1tb-ssd"
      },
      {
        "image_label": "Product Image,1 of 4",
        "item_title": "Macbook Air M3",
        "last_inbound_message": null,
        "last_outbound_message": null,
        "last_updated": "2026-03-22T16:37:29-07:00",
        "location_hint": null,
        "message_status": "sent",
        "price": "$600",
        "seller_name": null,
        "seller_rating": null,
        "thread_key": "macbook-air-m3"
      },
      {
        "image_label": "Product Image,1 of 5",
        "item_title": "Canon RF 35mm f/1.8 Macro IS STM Lens",
        "last_inbound_message": "Yes, available for pickup in West Seattle off 49th Ave SW near Juneau",
        "last_outbound_message": "Hi, I\u2019m interested in the Canon RF 35mm f/1.8 Macro IS STM Lens. Is it still available?",
        "last_updated": "2026-03-22T12:36:23-07:00",
        "location_hint": "Yes, available for pickup in West Seattle off 49th Ave SW near Juneau",
        "message_status": "seller_confirmed_available",
        "price": "$325",
        "seen_status": "Seen by Joshua Carlin",
        "seller_name": "Joshua",
        "seller_rating": "5.0 (13 reviews of Joshua)",
        "thread_key": "joshua-canon-rf-35mm-f-1-8-macro-is-stm-lens"
      }
    ],
    "inspected_items": [
      {
        "description_excerpt": "$300 marked down from $450Apple iPad Pro 11\u2011inch",
        "draft_or_message": "$280 \u00b7 Selling 2 monitors + dock station",
        "image_label": null,
        "item_key": "sell",
        "item_title": "Sell",
        "last_updated": "2026-03-26T01:07:10-07:00",
        "location_hint": "Location: Bothell, WA",
        "message_status": null,
        "price": "$300 marked down from $450Apple iPad Pro 11\u2011inch",
        "seller_name": "$300 $450",
        "seller_rating": null
      },
      {
        "description_excerpt": "$120 can negotiate on price. Works completely fine I just don\u2019t play games as much anymore. Will take anything from around $120",
        "draft_or_message": null,
        "image_label": "Product Image,1 of 4",
        "item_key": "sceptre-27-inch-240hz-gaming-monitor",
        "item_title": "Sceptre 27-inch 240hz gaming monitor",
        "last_updated": "2026-03-26T01:07:05-07:00",
        "location_hint": null,
        "message_status": null,
        "price": "$120",
        "seller_name": null,
        "seller_rating": null
      },
      {
        "description_excerpt": "Roberto Braulio, Joined Facebook in 2010",
        "draft_or_message": null,
        "image_label": "Product Image,1 of 1",
        "item_key": "playstation-5",
        "item_title": "Playstation 5",
        "last_updated": "2026-03-26T01:05:21-07:00",
        "location_hint": null,
        "message_status": null,
        "price": "$400",
        "seller_name": "Just listed",
        "seller_rating": null
      },
      {
        "description_excerpt": "Hi, I'm interested in the HP Omen Max 16. Is it still available?",
        "draft_or_message": "i7 255hx, 32gb ram, 512 gb + 2tb ssds, 240hz 2560x1600p OLED screen, wifi 7",
        "image_label": "Product Image,1 of 7",
        "item_key": "hp-omen-max-16-5080-i7-255hx-32gb-ram-512-gb-2tb-ssds-240hz-2560x1600p-oled-screen-wifi-7",
        "item_title": "HP Omen Max 16 - 5080, i7 255hx, 32gb ram, 512 gb + 2tb ssds, 240hz 2560x1600p OLED screen, wifi 7",
        "last_updated": "2026-03-26T00:49:13-07:00",
        "location_hint": null,
        "message_status": "sent",
        "price": "$1,900",
        "seller_name": null,
        "seller_rating": null
      },
      {
        "description_excerpt": "Hey, if everything checks out, would you take $550 for the 2021 MacBook Pro M1 Pro chip?",
        "draft_or_message": "if everything checks out, would you take $550 for the 2021 MacBook Pro M1 Pro chip?",
        "image_label": "Product Image,1 of 7",
        "item_key": "2021-macbook-pro-m1-pro-chip",
        "item_title": "2021 MacBook Pro M1 Pro chip",
        "last_updated": "2026-03-26T00:47:08-07:00",
        "location_hint": null,
        "message_status": "sent",
        "price": "$800",
        "seller_name": null,
        "seller_rating": null
      },
      {
        "description_excerpt": "Samsung S23. No cracks or scratches. Normal minor usage and cones with case.",
        "draft_or_message": null,
        "image_label": "Product Image,1 of 2",
        "item_key": "samsung-s23",
        "item_title": "Samsung S23",
        "last_updated": "2026-03-26T00:44:20-07:00",
        "location_hint": null,
        "message_status": null,
        "price": "$200",
        "seller_name": "Just listed",
        "seller_rating": null
      },
      {
        "description_excerpt": "Hi, I'm interested in the motherboard combo. Is it still available?",
        "draft_or_message": null,
        "image_label": "Product Image,1 of 1",
        "item_key": "motherboard-with-cpu-and-ram",
        "item_title": "motherboard with cpu and ram",
        "last_updated": "2026-03-26T00:43:16-07:00",
        "location_hint": null,
        "message_status": "sent",
        "price": "$300",
        "seller_name": null,
        "seller_rating": null
      },
      {
        "description_excerpt": "Hey, interested in the Apple MacBook Pro 16\" A2141 2019 \u2013 i9 2.30GHz \u2013 32GB RAM \u2013 1TB SSD \u2013 Retina EUC. Still available?",
        "draft_or_message": "interested in the Apple MacBook Pro 16\" A2141 2019 \u2013 i9 2.30GHz \u2013 32GB RAM \u2013 1TB SSD \u2013 Retina EUC. Still available?",
        "image_label": "Product Image,1 of 9",
        "item_key": "apple-macbook-pro-16-a2141-2019-i9-2-30ghz-32gb-ram-1tb-ssd-retina-euc",
        "item_title": "Apple MacBook Pro 16\" A2141 2019 \u2013 i9 2.30GHz \u2013 32GB RAM \u2013 1TB SSD \u2013 Retina EUC",
        "last_updated": "2026-03-26T00:40:17-07:00",
        "location_hint": null,
        "message_status": "sent",
        "price": "$429",
        "seller_name": "Just listed",
        "seller_rating": null
      },
      {
        "description_excerpt": "Hey, what condition is the Alienware m16 R2 Gaming Laptop | Ultra 9 | RTX 4070 | 32GB RAM | 1TB SSD | 240Hz QHD | 2025 in? Any scratches, dents, or issues?",
        "draft_or_message": "what condition is the Alienware m16 R2 Gaming Laptop | Ultra 9 | RTX 4070 | 32GB RAM | 1TB SSD | 240Hz QHD | 2025 in? Any scratches, dents, or issues?",
        "image_label": null,
        "item_key": "alienware-m16-r2-gaming-laptop-ultra-9-rtx-4070-32gb-ram-1tb-ssd-240hz-qhd-2025",
        "item_title": "Alienware m16 R2 Gaming Laptop | Ultra 9 | RTX 4070 | 32GB RAM | 1TB SSD | 240Hz QHD | 2025",
        "last_updated": "2026-03-26T00:39:04-07:00",
        "location_hint": null,
        "message_status": "sent",
        "price": "$1,150",
        "seller_name": null,
        "seller_rating": null
      },
      {
        "description_excerpt": "Hi, I'm interested in the MacBook Pro 15\" 2017 (A1707) \u2013 i7, 16GB RAM, 500GB SSD. Is it still available?",
        "draft_or_message": "16GB RAM, 500GB SSD",
        "image_label": "Product Image,1 of 3",
        "item_key": "macbook-pro-15-2017-a1707-i7-16gb-ram-500gb-ssd",
        "item_title": "MacBook Pro 15\" 2017 (A1707) \u2013 i7, 16GB RAM, 500GB SSD",
        "last_updated": "2026-03-26T00:31:44-07:00",
        "location_hint": null,
        "message_status": "sent",
        "price": "$230",
        "seller_name": "Just listed",
        "seller_rating": null
      },
      {
        "description_excerpt": "Nice little setup (Pc & monitor) throwing in led keyboard and",
        "draft_or_message": null,
        "image_label": null,
        "item_key": "pc",
        "item_title": "PC",
        "last_updated": "2026-03-26T00:29:30-07:00",
        "location_hint": null,
        "message_status": "sent",
        "price": "$800",
        "seller_name": "Just listed",
        "seller_rating": null
      },
      {
        "description_excerpt": "Up for sale is a practically new gaming PC that I built myself little over a year ago. Selling due to lack of usage. This thing has been turned on less than 100 times. The 32GB DDR5 RAM is worth over $350 alone. Refer to the HWINFO screenshot for full specs Specs: - 32GB DDR5 RAM @ 6000mhz - AMD Ryzen 5 7600 - XFX RX 6700 XT 12GB - ASUS TUF GAMING B650-PLUS WIFI Motherboard - Corsair CX650 PSU (650 watts) - Western Digital Black NVMe1TB SSD - CM Hyper 212 CPU Cooler Available for PICK-UP ONLY. Located in north Ballard. Selling as a complete unit. Do not reach out asking to part-out. Come check it out in-person and feel free to shoot me any questions.",
        "draft_or_message": null,
        "image_label": "Product Image,1 of 3",
        "item_key": "full-pc-32gb-ddr5-ram-ryzen-5-7600-rx-6700-xt",
        "item_title": "[Full PC] 32GB DDR5 RAM / Ryzen 5 7600 / RX 6700 XT /",
        "last_updated": "2026-03-26T00:28:39-07:00",
        "location_hint": null,
        "message_status": "sent",
        "price": "$1,100",
        "seller_name": null,
        "seller_rating": null
      },
      {
        "description_excerpt": "Mac book pro 16\" screen M2 32gb ram 1 tb hard drive Comes with apple charger & cable",
        "draft_or_message": null,
        "image_label": "Product Image,1 of 2",
        "item_key": "2023-macbook-pro",
        "item_title": "2023 MacBook pro",
        "last_updated": "2026-03-26T00:21:19-07:00",
        "location_hint": null,
        "message_status": "sent",
        "price": "$1,200",
        "seller_name": null,
        "seller_rating": null
      },
      {
        "description_excerpt": "The Sony 200-600mm f/4.5-5.6 G OSS FE lens and the Sony 1.4x Teleconverter can be purchased",
        "draft_or_message": null,
        "image_label": "Product Image,1 of 1",
        "item_key": "sony-lens",
        "item_title": "Sony lens",
        "last_updated": "2026-03-26T00:19:26-07:00",
        "location_hint": null,
        "message_status": "sent",
        "price": "$1,700",
        "seller_name": "Just listed",
        "seller_rating": null
      },
      {
        "description_excerpt": "Selling my old iPhone 13 Pro Max 256 GB as I\u2019ve since upgraded.",
        "draft_or_message": null,
        "image_label": "Product Image,1 of 6",
        "item_key": "iphone-13-pro-max",
        "item_title": "iPhone 13 Pro Max",
        "last_updated": "2026-03-26T00:18:09-07:00",
        "location_hint": null,
        "message_status": "sent",
        "price": "$350",
        "seller_name": "Just listed",
        "seller_rating": null
      },
      {
        "description_excerpt": "Fully unlocked for any carrier, no sim restrictions, factory reset no iCloud ! 128GB ! 87% battery health",
        "draft_or_message": null,
        "image_label": "Product Image,1 of 4",
        "item_key": "apple-iphone-14-pro-5g-unlocked",
        "item_title": "Apple iPhone 14 Pro 5G Unlocked",
        "last_updated": "2026-03-26T00:17:28-07:00",
        "location_hint": null,
        "message_status": "sent",
        "price": "$420",
        "seller_name": null,
        "seller_rating": null
      },
      {
        "description_excerpt": "Work flawlessly. No dead pixels, no scratches. I live near the Space Needle and the Sphere https://www.bestbuy.com/site/reviews/aoc-pro-line-u3277pwqu-31-5-lcd-4k-uhd-monitor-black-silver/6177630 https://aoc.com/us/monitors/u3277pwqu",
        "draft_or_message": null,
        "image_label": "Product Image,1 of 3",
        "item_key": "monitor-32-4k-uhd-3840x2160",
        "item_title": "Monitor 32\" 4K UHD 3840x2160",
        "last_updated": "2026-03-26T00:14:52-07:00",
        "location_hint": null,
        "message_status": "sent",
        "price": "$200",
        "seller_name": "Just listed",
        "seller_rating": null
      },
      {
        "description_excerpt": "Great PC. Runs any game you can think of on medium to high settings.",
        "draft_or_message": null,
        "image_label": "Product Image,1 of 2",
        "item_key": "rtx-3060-gaming-pc",
        "item_title": "RTX 3060 Gaming PC",
        "last_updated": "2026-03-26T00:13:03-07:00",
        "location_hint": null,
        "message_status": "sent",
        "price": "$650",
        "seller_name": "Just listed",
        "seller_rating": null
      },
      {
        "description_excerpt": "Built this PC myself in 2023, but moving and looking to take a break from gaming. Works very well, no lag when playing high computational games. Intel i7 CPU and Nvidia RTX 3080 and 32 GB RAM. Specs included in photos. Took care of PC well, no problems whatsoever. I have an external wifi booster included. Pickup only in South Seattle",
        "draft_or_message": null,
        "image_label": "Product Image,1 of 3",
        "item_key": "gaming-pc",
        "item_title": "Gaming PC",
        "last_updated": "2026-03-25T14:58:05-07:00",
        "location_hint": "Built this PC myself in 2023, but moving and looking to take a break from gaming. Works very well, no lag when playing high computational games. Intel i7 CPU and Nvidia RTX 3080 and 32 GB RAM. Specs included in photos. Took care of PC well, no problems whatsoever. I have an external wifi booster included. Pickup only in South Seattle",
        "message_status": null,
        "price": "$850",
        "seller_name": "Just listed",
        "seller_rating": null
      },
      {
        "description_excerpt": "27\u201d QHD 2560 x 1440 at 60 Hz with USB-C hub built-in",
        "draft_or_message": null,
        "image_label": "Product Image,1 of 7",
        "item_key": "dell-27-inch-usb-c-hub-computer-monitor-p2723de",
        "item_title": "Dell 27 Inch USB-C Hub Computer Monitor - P2723DE",
        "last_updated": "2026-03-25T14:56:09-07:00",
        "location_hint": null,
        "message_status": "sent",
        "price": "$100",
        "seller_name": "Just listed",
        "seller_rating": null
      },
      {
        "description_excerpt": "Apple iPhone 16 Pro Max in white with 256GB storage. The phone is in excellent condition, with",
        "draft_or_message": null,
        "image_label": "Product Image,1 of 2",
        "item_key": "apple-iphone-16-pro-max-256gb-white-excellent-condition",
        "item_title": "Apple iPhone 16 Pro Max \u2013 256GB \u2013 White \u2013 Excellent Condition",
        "last_updated": "2026-03-25T14:55:29-07:00",
        "location_hint": null,
        "message_status": "sent",
        "price": "$700",
        "seller_name": "Just listed",
        "seller_rating": null
      },
      {
        "description_excerpt": "Microsoft Surface Laptop 4 in fantastic condition. Reset to the factory settings unlocked and is ready",
        "draft_or_message": null,
        "image_label": "Product Image,1 of 5",
        "item_key": "microsoft-surface-laptop-4-32gb-1tb-ssd",
        "item_title": "Microsoft Surface Laptop 4 32GB 1TB SSD",
        "last_updated": "2026-03-25T14:54:48-07:00",
        "location_hint": null,
        "message_status": "sent",
        "price": "$350",
        "seller_name": "Just listed",
        "seller_rating": null
      },
      {
        "description_excerpt": "16 GB unified memory 500 GB storage In original box with charger",
        "draft_or_message": "15 inch",
        "image_label": "Product Image,1 of 2",
        "item_key": "macbook-air-m4-15-inch",
        "item_title": "MacBook Air M4, 15 inch",
        "last_updated": "2026-03-22T21:04:40-07:00",
        "location_hint": null,
        "message_status": null,
        "price": "$1,000",
        "seller_name": null,
        "seller_rating": null
      },
      {
        "description_excerpt": "Selling my Sony Alpha a6700 mirrorless camera body in excellent condition. Lightly used and well cared for \u2014 sensor, LCD, EVF, and all controls are in perfect working order. What's included: - Sony a6700 body - Sony E-mount body cap - NP-FZ100 battery Key specs: - 26MP APS-C back-illuminated Exmor R sensor - AI-powered subject recognition autofocus (759 phase-detect points) - 4K 120fps video / 10-bit 4:2:2 recording - 5-axis in-body image stabilization (IBIS) - Fully articulating vari-angle touchscreen LCD - Built-in EVF - Dust & moisture sealed magnesium alloy body - Sony E-mount (compatible with all Sony E-mount lenses) Condition: Lightly used, no visible damage. Sensor is clean. Screen is scratch-free. $1,150 \u2014 firm. Local pickup only in Seattle. No shipping. Venmo or Zelle preferred. Serious buyers only",
        "draft_or_message": null,
        "image_label": "Product Image,1 of 5",
        "item_key": "sony-a6700-mirrorless-camera-body-lightly-used-local-pickup-seattle",
        "item_title": "Sony a6700 Mirrorless Camera Body \u2014 Lightly Used | Local Pickup Seattle",
        "last_updated": "2026-03-22T20:33:54-07:00",
        "location_hint": "Sony a6700 Mirrorless Camera Body \u2014 Lightly Used | Local Pickup Seattle",
        "message_status": null,
        "price": "$1,150",
        "seller_name": "Just listed",
        "seller_rating": null
      },
      {
        "description_excerpt": "Hi, is this available? Any dead pixels or scratches?",
        "draft_or_message": null,
        "image_label": "Product Image,1 of 6",
        "item_key": "asus-tuf-27-2k-g-sync-gaming-monitor",
        "item_title": "Asus TUF 27\" 2K G-SYNC Gaming Monitor",
        "last_updated": "2026-03-22T18:44:57-07:00",
        "location_hint": null,
        "message_status": null,
        "price": "$100",
        "seller_name": "Just listed",
        "seller_rating": null
      }
    ],
    "threads": [
      {
        "item_title": "PC",
        "last_inbound_message": null,
        "last_outbound_message": "Hi, is this available?",
        "last_updated": "2026-03-26T01:10:55-07:00",
        "location_hint": null,
        "messages": [
          {
            "direction": "outbound",
            "speaker": "Owen",
            "text": "Hi, is this available?"
          }
        ],
        "seen_status": null,
        "seller_name": "Joshua",
        "seller_rating": null,
        "thread_key": "joshua-pc",
        "thread_title": "Joshua \u00b7 PC"
      },
      {
        "item_title": "Gaming PC",
        "last_inbound_message": "No",
        "last_outbound_message": "350?",
        "last_updated": "2026-03-25T23:01:51-07:00",
        "location_hint": null,
        "messages": [
          {
            "direction": "outbound",
            "speaker": "Owen",
            "text": "350?"
          },
          {
            "direction": "inbound",
            "speaker": "Brandon",
            "text": "No"
          }
        ],
        "seen_status": "Seen by Brandon Pellham",
        "seller_name": "Brandon",
        "seller_rating": "4.2 (5 reviews of Brandon)",
        "thread_key": "brandon-gaming-pc",
        "thread_title": "Brandon \u00b7 Gaming PC"
      },
      {
        "item_title": "Canon RF 35mm f/1.8 Macro IS STM Lens",
        "last_inbound_message": "Yes, available for pickup in West Seattle off 49th Ave SW near Juneau",
        "last_outbound_message": "Hi, I\u2019m interested in the Canon RF 35mm f/1.8 Macro IS STM Lens. Is it still available?",
        "last_updated": "2026-03-22T12:36:23-07:00",
        "location_hint": "Yes, available for pickup in West Seattle off 49th Ave SW near Juneau",
        "messages": [
          {
            "direction": "outbound",
            "speaker": "Owen",
            "text": "Hi, I\u2019m interested in the Canon RF 35mm f/1.8 Macro IS STM Lens. Is it still available?"
          },
          {
            "direction": "inbound",
            "speaker": "Joshua",
            "text": "Yes, available for pickup in West Seattle off 49th Ave SW near Juneau"
          }
        ],
        "seen_status": "Seen by Joshua Carlin",
        "seller_name": "Joshua",
        "seller_rating": "5.0 (13 reviews of Joshua)",
        "thread_key": "joshua-canon-rf-35mm-f-1-8-macro-is-stm-lens",
        "thread_title": "Joshua \u00b7 Canon RF 35mm f/1.8 Macro IS STM Lens"
      }
    ]
  },
  "last_updated": "2026-03-26T01:10:59-07:00",
  "package_name": "com.facebook.katana",
  "recent_screens": [
    {
      "activity_name": ".LoginActivity",
      "clickable_text": [
        "Sell",
        "For you",
        "Local",
        "Tap to view categories and more",
        "Location: Bothell, WA",
        "$200\u00a0\u00b7\u00a0EVGA RTX 3070 8GB",
        "Just listed, $450\u00a0\u00b7\u00a0\u26a1 Gigabyte GeForce RTX 4070 12GB \u2013 Excellent Condition, Ready to Game!",
        "$850\u00a0\u00b7\u00a0Surface Laptop 6 For Business i7, 64gb ram 1tb SSD",
        "Just listed, $690\u00a0\u00b7\u00a0MacBook Air M2 15\"",
        "Nearby, $1,600\u00a0\u00b7\u00a0Thinkpad P15 i9 vPro 1 TB 128GB RAM Nvidia GPU",
        "Just listed, $100\u00a0\u00b7\u00a0Gigabyte Z390 AORUS PRO WIFI with i5-9600k CPU",
        "Menu | Marketplace | Tap to view your Marketplace account | What do you want to buy?"
      ],
      "last_seen_at": "2026-03-26T00:49:25-07:00",
      "package_name": "com.facebook.katana",
      "screen_id": "com-facebook-katana-loginactivity-a54ffcd6367b82ed",
      "seen_count": 1,
      "visible_text": [
        "Sell",
        "For you, Tab, 1 of 2",
        "For you",
        "Local, Tab, 2 of 2",
        "Local",
        "Tap to view categories and more",
        "More",
        "Today's picks",
        "Location: Bothell, WA",
        "Bothell, WA",
        "$200\u00a0\u00b7\u00a0EVGA RTX 3070 8GB",
        "Just listed, $450\u00a0\u00b7\u00a0\u26a1 Gigabyte GeForce RTX 4070 12GB \u2013 Excellent Condition, Ready to Game!"
      ]
    },
    {
      "activity_name": ".activity.react.ImmersiveReactActivity",
      "clickable_text": [
        "Close",
        "Navigate to Search",
        "More actions",
        "Product Image,1 of 1",
        "Like",
        "Comment",
        "Save",
        "Share",
        "Hi, is this available?",
        "Send",
        "New never used",
        "Seller"
      ],
      "last_seen_at": "2026-03-26T01:05:21-07:00",
      "package_name": "com.facebook.katana",
      "screen_id": "com-facebook-katana-activity-react-immersivereactactivity-ccdf9f9ba107ebda",
      "seen_count": 2,
      "visible_text": [
        "Close",
        "Navigate to Search",
        "More actions",
        "Product Image,1 of 1",
        "Playstation 5",
        "$400",
        "Just listed\u00a0\u00b7\u00a06 hours ago",
        "Like",
        "Comment",
        "Save",
        "Share",
        "Message seller"
      ]
    },
    {
      "activity_name": ".LoginActivity",
      "clickable_text": [
        "Sell",
        "For you",
        "Local",
        "Tap to view categories and more",
        "$400\u00a0\u00b7\u00a0Playstation 5",
        "$375\u00a0\u00b7\u00a0Gaming computer",
        "Just listed, $320\u00a0\u00b7\u00a0Dell PRECISION T7810 + monitor",
        "$75\u00a0\u00b7\u00a0Sceptre m24 165hz 24 inch gaming monitor",
        "Just listed, $215\u00a0\u00b7\u00a0EVGA 3060ti ftw3",
        "$10\u00a0\u00b7\u00a0Crystal Clear Screen Protector for iPhone 17/16 Pro Max",
        "Menu | Marketplace | Tap to view your Marketplace account | What do you want to buy?",
        "Menu"
      ],
      "last_seen_at": "2026-03-26T01:05:26-07:00",
      "package_name": "com.facebook.katana",
      "screen_id": "com-facebook-katana-loginactivity-2c00940f65d54140",
      "seen_count": 5,
      "visible_text": [
        "Sell",
        "For you, Tab, 1 of 2",
        "For you",
        "Local, Tab, 2 of 2",
        "Local",
        "Tap to view categories and more",
        "More",
        "$400\u00a0\u00b7\u00a0Playstation 5",
        "$375\u00a0\u00b7\u00a0Gaming computer",
        "Just listed, $320\u00a0\u00b7\u00a0Dell PRECISION T7810 + monitor",
        "Just listed",
        "$320\u00a0\u00b7\u00a0Dell PRECISION T7810 + monitor"
      ]
    },
    {
      "activity_name": ".activity.react.ImmersiveReactActivity",
      "clickable_text": [
        "Close",
        "Navigate to Search",
        "More actions",
        "Product Image,1 of 4",
        "Like",
        "Comment",
        "Save",
        "Share",
        "Hi, is this available?",
        "Send",
        "$120 can negotiate on price.\nWorks completely fine I just don\u2019t play games as | much anymore. | See more",
        "See more"
      ],
      "last_seen_at": "2026-03-26T01:05:36-07:00",
      "package_name": "com.facebook.katana",
      "screen_id": "com-facebook-katana-activity-react-immersivereactactivity-395d4184b67b3a51",
      "seen_count": 1,
      "visible_text": [
        "Close",
        "Navigate to Search",
        "More actions",
        "Product Image,1 of 4",
        "Sceptre 27-inch 240hz gaming monitor",
        "$120",
        "Like",
        "Comment",
        "Save",
        "Share",
        "Message seller",
        "Hi, is this available?"
      ]
    },
    {
      "activity_name": ".activity.react.ImmersiveReactActivity",
      "clickable_text": [
        "Close",
        "Navigate to Search",
        "More actions",
        "Product Image,1 of 4",
        "Like",
        "Comment",
        "Save",
        "Share",
        "Hi, is this available?",
        "Send",
        "$120 can negotiate on price.\nWorks completely fine I just don\u2019t play games as much anymore. \nWill take anything from around $120 | See less",
        "See less"
      ],
      "last_seen_at": "2026-03-26T01:07:05-07:00",
      "package_name": "com.facebook.katana",
      "screen_id": "com-facebook-katana-activity-react-immersivereactactivity-045f26ac70988f24",
      "seen_count": 2,
      "visible_text": [
        "Close",
        "Navigate to Search",
        "More actions",
        "Product Image,1 of 4",
        "Sceptre 27-inch 240hz gaming monitor",
        "$120",
        "Like",
        "Comment",
        "Save",
        "Share",
        "Message seller",
        "Hi, is this available?"
      ]
    },
    {
      "activity_name": ".LoginActivity",
      "clickable_text": [
        "Sell",
        "For you",
        "Local",
        "Tap to view categories and more",
        "$300 marked down from $450Apple iPad Pro 11\u2011inch",
        "$120\u00a0\u00b7\u00a0Sceptre 27-inch 240hz gaming monitor",
        "Just listed, $380\u00a0\u00b7\u00a0Rtx 3080 Ftw3",
        "$500 marked down from $550Samsung Odyssey OLED 27\u201d 240hz 1440p Gaming Monitor",
        "Just listed, $100\u00a0\u00b7\u00a0Barely used - Harman Kardon Aura Studio 3",
        "$480\u00a0\u00b7\u00a0[Brand New Sealed] PlayStation 5 Disc Console 1TB - Fortnite Flowering Chaos Bundle",
        "Just listed, $90\u00a0\u00b7\u00a0Moving Sale \u2013 Must Go Soon",
        "$1\u00a0\u00b7\u00a0WE BUY IPHONE SAMSUNG!!! I BUY iPADS, MACBOOK, WATCHES FOR CASH"
      ],
      "last_seen_at": "2026-03-26T01:07:10-07:00",
      "package_name": "com.facebook.katana",
      "screen_id": "com-facebook-katana-loginactivity-c1e9a36ac35efca9",
      "seen_count": 2,
      "visible_text": [
        "Sell",
        "For you, Tab, 1 of 2",
        "For you",
        "Local, Tab, 2 of 2",
        "Local",
        "Tap to view categories and more",
        "More",
        "$300 marked down from $450Apple iPad Pro 11\u2011inch",
        "$300 $450\u00a0\u00b7\u00a0Apple iPad Pro 11\u2011inch",
        "$120\u00a0\u00b7\u00a0Sceptre 27-inch 240hz gaming monitor",
        "Just listed, $380\u00a0\u00b7\u00a0Rtx 3080 Ftw3",
        "Just listed"
      ]
    },
    {
      "activity_name": ".activity.react.ImmersiveReactActivity",
      "clickable_text": [
        "\ufffc, Owen Uj, View Marketplace profile",
        "10+ saved items, ,",
        "2 messages, ,",
        "10+ reviews to write, ,",
        "Recently viewed, ,",
        "Your listings (13)",
        "Orders to fill",
        "Quick actions",
        "Marketplace followers",
        "All selling activities",
        "Following",
        "Marketplace access, You have full access."
      ],
      "last_seen_at": "2026-03-26T01:08:57-07:00",
      "package_name": "com.facebook.katana",
      "screen_id": "com-facebook-katana-activity-react-immersivereactactivity-e09b9ea7bc4bf2bc",
      "seen_count": 2,
      "visible_text": [
        "\ufffc, Owen Uj, View Marketplace profile",
        "\ufffc",
        "Owen Uj",
        "View Marketplace profile",
        "10+ saved items, ,",
        "10+ saved items",
        "2 messages, ,",
        "2 messages",
        "10+ reviews to write, ,",
        "10+ reviews to write",
        "Recently viewed, ,",
        "Recently viewed"
      ]
    },
    {
      "activity_name": "com.facebook.messaginginblue.inbox.activities.InboxActivity",
      "clickable_text": [
        "Back",
        "DebySue \u00b7 2023 MacBook pro, Unread, DebySue: Yes",
        "Jordan \u00b7 HP Omen Max 16 - 5080, i7 255hx, 32gb ram, 512 gb + 2tb ssds, 240hz 2560x1600p OLED screen, wifi 7, Unread, Jordan: Yes",
        "Crystal \u00b7 2021 MacBook Pro M1 Pro chip, Read, You: Hey, if everything checks out, would you take $550 for the 2021 MacBook Pro M1 Pro chip?",
        "David \u00b7 motherboard with cpu and ram, Read, You: Hi, I'm interested in the motherboard combo. Is it still available?",
        "Angela \u00b7 Apple MacBook Pro 16\" A2141 2019 \u2013 i9 2.30GHz \u2013 32GB RAM \u2013 1TB SSD \u2013 Retina EUC, Read, You: Hey, interested in the Apple MacBook Pro 16\" A2141 2019 \u2013 i9 2.30GHz \u2013 32GB RAM \u2013 1TB SSD \u2013 Retina EUC. Still available?",
        "Nitin \u00b7 Alienware m16 R2 Gaming Laptop | Ultra 9 | RTX 4070 | 32GB RAM | 1TB SSD | 240Hz QHD | 2025, Read, You: Hey, what condition is the Alienware m16 R2 Gaming Laptop | Ultra 9 | RTX 4070 | 32GB RAM | 1TB SSD | 240Hz QHD | 2025 in? Any scratches, dents, or issues?",
        "Adam \u00b7 MacBook Pro 15\" 2017 (A1707) \u2013 i7, 16GB RAM, 500GB SSD, Read, You: Hi, I'm interested in the MacBook Pro 15\" 2017 (A1707) \u2013 i7, 16GB RAM, 500GB SSD. Is it still available?",
        "Joshua \u00b7 PC, Read, You: Hi, is this available?",
        "Shoumik \u00b7 [Full PC] 32GB DDR5 RAM / Ryzen 5 7600 / RX 6700 XT /, Read, You: Hi, is this available?",
        "Amber Ann \u00b7 Sony Alpha 7 III with FE 50mm f/1.8 Lens, Read, You: \udb80\udc00"
      ],
      "last_seen_at": "2026-03-26T01:09:01-07:00",
      "package_name": "com.facebook.katana",
      "screen_id": "com-facebook-katana-com-facebook-messaginginblue-inbox-activities-inboxactivity-67d9f5bf4803897a",
      "seen_count": 1,
      "visible_text": [
        "Back",
        "Marketplace inbox",
        "Restore chat history.",
        "DebySue \u00b7 2023 MacBook pro, Unread, DebySue: Yes",
        "Jordan \u00b7 HP Omen Max 16 - 5080, i7 255hx, 32gb ram, 512 gb + 2tb ssds, 240hz 2560x1600p OLED screen, wifi 7, Unread, Jordan: Yes",
        "Crystal \u00b7 2021 MacBook Pro M1 Pro chip, Read, You: Hey, if everything checks out, would you take $550 for the 2021 MacBook Pro M1 Pro chip?",
        "David \u00b7 motherboard with cpu and ram, Read, You: Hi, I'm interested in the motherboard combo. Is it still available?",
        "Angela \u00b7 Apple MacBook Pro 16\" A2141 2019 \u2013 i9 2.30GHz \u2013 32GB RAM \u2013 1TB SSD \u2013 Retina EUC, Read, You: Hey, interested in the Apple MacBook Pro 16\" A2141 2019 \u2013 i9 2.30GHz \u2013 32GB RAM \u2013 1TB SSD \u2013 Retina EUC. Still available?",
        "Nitin \u00b7 Alienware m16 R2 Gaming Laptop | Ultra 9 | RTX 4070 | 32GB RAM | 1TB SSD | 240Hz QHD | 2025, Read, You: Hey, what condition is the Alienware m16 R2 Gaming Laptop | Ultra 9 | RTX 4070 | 32GB RAM | 1TB SSD | 240Hz QHD | 2025 in? Any scratches, dents, or issues?",
        "Adam \u00b7 MacBook Pro 15\" 2017 (A1707) \u2013 i7, 16GB RAM, 500GB SSD, Read, You: Hi, I'm interested in the MacBook Pro 15\" 2017 (A1707) \u2013 i7, 16GB RAM, 500GB SSD. Is it still available?",
        "Joshua \u00b7 PC, Read, You: Hi, is this available?",
        "Shoumik \u00b7 [Full PC] 32GB DDR5 RAM / Ryzen 5 7600 / RX 6700 XT /, Read, You: Hi, is this available?"
      ]
    },
    {
      "activity_name": "com.facebook.messaginginblue.inbox.activities.InboxActivity",
      "clickable_text": [
        "Back",
        "Shoumik \u00b7 [Full PC] 32GB DDR5 RAM / Ryzen 5 7600 / RX 6700 XT /, Unread, Shoumik: Yes, are you interested?",
        "DebySue \u00b7 2023 MacBook pro, Unread, DebySue: Yes",
        "Jordan \u00b7 HP Omen Max 16 - 5080, i7 255hx, 32gb ram, 512 gb + 2tb ssds, 240hz 2560x1600p OLED screen, wifi 7, Unread, Jordan: Yes",
        "Crystal \u00b7 2021 MacBook Pro M1 Pro chip, Read, You: Hey, if everything checks out, would you take $550 for the 2021 MacBook Pro M1 Pro chip?",
        "David \u00b7 motherboard with cpu and ram, Read, You: Hi, I'm interested in the motherboard combo. Is it still available?",
        "Angela \u00b7 Apple MacBook Pro 16\" A2141 2019 \u2013 i9 2.30GHz \u2013 32GB RAM \u2013 1TB SSD \u2013 Retina EUC, Read, You: Hey, interested in the Apple MacBook Pro 16\" A2141 2019 \u2013 i9 2.30GHz \u2013 32GB RAM \u2013 1TB SSD \u2013 Retina EUC. Still available?",
        "Nitin \u00b7 Alienware m16 R2 Gaming Laptop | Ultra 9 | RTX 4070 | 32GB RAM | 1TB SSD | 240Hz QHD | 2025, Read, You: Hey, what condition is the Alienware m16 R2 Gaming Laptop | Ultra 9 | RTX 4070 | 32GB RAM | 1TB SSD | 240Hz QHD | 2025 in? Any scratches, dents, or issues?",
        "Adam \u00b7 MacBook Pro 15\" 2017 (A1707) \u2013 i7, 16GB RAM, 500GB SSD, Read, You: Hi, I'm interested in the MacBook Pro 15\" 2017 (A1707) \u2013 i7, 16GB RAM, 500GB SSD. Is it still available?",
        "Joshua \u00b7 PC, Read, You: Hi, is this available?",
        "Amber Ann \u00b7 Sony Alpha 7 III with FE 50mm f/1.8 Lens, Read, You: \udb80\udc00"
      ],
      "last_seen_at": "2026-03-26T01:09:43-07:00",
      "package_name": "com.facebook.katana",
      "screen_id": "com-facebook-katana-com-facebook-messaginginblue-inbox-activities-inboxactivity-5af9fe18cbda14e9",
      "seen_count": 1,
      "visible_text": [
        "Back",
        "Marketplace inbox",
        "Restore chat history.",
        "Shoumik \u00b7 [Full PC] 32GB DDR5 RAM / Ryzen 5 7600 / RX 6700 XT /, Unread, Shoumik: Yes, are you interested?",
        "DebySue \u00b7 2023 MacBook pro, Unread, DebySue: Yes",
        "Jordan \u00b7 HP Omen Max 16 - 5080, i7 255hx, 32gb ram, 512 gb + 2tb ssds, 240hz 2560x1600p OLED screen, wifi 7, Unread, Jordan: Yes",
        "Crystal \u00b7 2021 MacBook Pro M1 Pro chip, Read, You: Hey, if everything checks out, would you take $550 for the 2021 MacBook Pro M1 Pro chip?",
        "David \u00b7 motherboard with cpu and ram, Read, You: Hi, I'm interested in the motherboard combo. Is it still available?",
        "Angela \u00b7 Apple MacBook Pro 16\" A2141 2019 \u2013 i9 2.30GHz \u2013 32GB RAM \u2013 1TB SSD \u2013 Retina EUC, Read, You: Hey, interested in the Apple MacBook Pro 16\" A2141 2019 \u2013 i9 2.30GHz \u2013 32GB RAM \u2013 1TB SSD \u2013 Retina EUC. Still available?",
        "Nitin \u00b7 Alienware m16 R2 Gaming Laptop | Ultra 9 | RTX 4070 | 32GB RAM | 1TB SSD | 240Hz QHD | 2025, Read, You: Hey, what condition is the Alienware m16 R2 Gaming Laptop | Ultra 9 | RTX 4070 | 32GB RAM | 1TB SSD | 240Hz QHD | 2025 in? Any scratches, dents, or issues?",
        "Adam \u00b7 MacBook Pro 15\" 2017 (A1707) \u2013 i7, 16GB RAM, 500GB SSD, Read, You: Hi, I'm interested in the MacBook Pro 15\" 2017 (A1707) \u2013 i7, 16GB RAM, 500GB SSD. Is it still available?",
        "Joshua \u00b7 PC, Read, You: Hi, is this available?"
      ]
    },
    {
      "activity_name": "com.facebook.messaging.msys.thread.fragment.MsysThreadViewActivity",
      "clickable_text": [
        "Back | Joshua \u00b7 PC | Marketplace listing | Chat profile",
        "Back",
        "Joshua \u00b7 PC",
        "Marketplace listing",
        "Chat profile | Joshua \u00b7 PC | Marketplace chats and your privacy",
        "Chat profile",
        "View seller profile",
        "Owen, Hi, is this available?",
        "Open camera.",
        "Open photo gallery.",
        "Open audio recorder.",
        "Message"
      ],
      "last_seen_at": "2026-03-26T01:09:47-07:00",
      "package_name": "com.facebook.katana",
      "screen_id": "com-facebook-katana-com-facebook-messaging-msys-thread-fragment-msysthreadviewactivity-b2176a003b6595ee",
      "seen_count": 1,
      "visible_text": [
        "Back",
        "Joshua \u00b7 PC",
        "Marketplace listing",
        "Chat profile",
        "Marketplace chats and your privacy",
        "You started this chat.\u00a0View seller profile",
        "View seller profile",
        "Owen, Hi, is this available?",
        "Sent 40 minutes ago",
        "Open camera.",
        "Open photo gallery.",
        "Open audio recorder."
      ]
    },
    {
      "activity_name": "com.facebook.messaging.msys.thread.fragment.MsysThreadViewActivity",
      "clickable_text": [
        "Back | Joshua \u00b7 PC | Marketplace listing | Chat profile",
        "Back",
        "Joshua \u00b7 PC",
        "Marketplace listing",
        "Chat profile | Joshua \u00b7 PC | Marketplace chats and your privacy",
        "Chat profile",
        "View seller profile",
        "Owen, Hi, is this available?",
        "Open camera.",
        "Open photo gallery.",
        "Open audio recorder.",
        "Message"
      ],
      "last_seen_at": "2026-03-26T01:10:55-07:00",
      "package_name": "com.facebook.katana",
      "screen_id": "com-facebook-katana-com-facebook-messaging-msys-thread-fragment-msysthreadviewactivity-5b06e14a74d4dd5c",
      "seen_count": 1,
      "visible_text": [
        "Back",
        "Joshua \u00b7 PC",
        "Marketplace listing",
        "Chat profile",
        "Marketplace chats and your privacy",
        "You started this chat.\u00a0View seller profile",
        "View seller profile",
        "Owen, Hi, is this available?",
        "Sent 41 minutes ago",
        "Open camera.",
        "Open photo gallery.",
        "Open audio recorder."
      ]
    },
    {
      "activity_name": "com.facebook.messaginginblue.threadsettings.surface.activity.MiBThreadSettingsSurfaceActivity",
      "clickable_text": [
        "Back",
        "Edit",
        "Mute notifications",
        "Messenger",
        "Nicknames",
        "See chat members",
        "Search in conversation",
        "Read receipts",
        "Block a Member",
        "Something's wrong",
        "Leave chat"
      ],
      "last_seen_at": "2026-03-26T01:10:59-07:00",
      "package_name": "com.facebook.katana",
      "screen_id": "com-facebook-katana-com-facebook-messaginginblue-threadsettings-surface-activity-mibthreadsettingssurfaceactivity-f3d9fa04c220ec1e",
      "seen_count": 1,
      "visible_text": [
        "Back",
        "Edit",
        "Joshua \u00b7 PC",
        "Mute notifications",
        "Messenger",
        "Customization",
        "Nicknames",
        "Chat info",
        "See chat members",
        "More actions",
        "Search in conversation",
        "Privacy and support"
      ]
    }
  ]
}